{
"type": "FeatureCollection",
"crs": { "type": "name", "properties": { "name": "urn:ogc:def:crs:OGC:1.3:CRS84" } },
"features": [
{ "type": "Feature", "properties": { "osm_type": "node", "osm_id": 7702620045, "name": "nan", "full_name": "natural tree", "lat": -36.7528858, "lng": 144.2840441 }, "geometry": { "type": "Point", "coordinates": [ 144.284044099999988, -36.7528858 ] } },
{ "type": "Feature", "properties": { "osm_type": "node", "osm_id": 7702620047, "name": "nan", "full_name": "natural tree", "lat": -36.7531423, "lng": 144.2843691 }, "geometry": { "type": "Point", "coordinates": [ 144.2843691, -36.7531423 ] } },
{ "type": "Feature", "properties": { "osm_type": "node", "osm_id": 7702620044, "name": "nan", "full_name": "natural tree", "lat": -36.7529919, "lng": 144.2842943 }, "geometry": { "type": "Point", "coordinates": [ 144.2842943, -36.7529919 ] } },
{ "type": "Feature", "properties": { "osm_type": "node", "osm_id": 7702620043, "name": "nan", "full_name": "natural tree", "lat": -36.7533555, "lng": 144.2834836 }, "geometry": { "type": "Point", "coordinates": [ 144.283483600000011, -36.7533555 ] } },
{ "type": "Feature", "properties": { "osm_type": "node", "osm_id": 7702620042, "name": "nan", "full_name": "natural tree", "lat": -36.7531207, "lng": 144.2836062 }, "geometry": { "type": "Point", "coordinates": [ 144.2836062, -36.7531207 ] } },
{ "type": "Feature", "properties": { "osm_type": "node", "osm_id": 7702620041, "name": "nan", "full_name": "natural tree", "lat": -36.7529735, "lng": 144.283735 }, "geometry": { "type": "Point", "coordinates": [ 144.283735, -36.7529735 ] } },
{ "type": "Feature", "properties": { "osm_type": "node", "osm_id": 7702590766, "name": "nan", "full_name": "natural tree", "lat": -36.7537987, "lng": 144.2829679 }, "geometry": { "type": "Point", "coordinates": [ 144.282967899999989, -36.7537987 ] } },
{ "type": "Feature", "properties": { "osm_type": "node", "osm_id": 7702590765, "name": "nan", "full_name": "natural tree", "lat": -36.7536912, "lng": 144.2829866 }, "geometry": { "type": "Point", "coordinates": [ 144.282986599999987, -36.7536912 ] } },
{ "type": "Feature", "properties": { "osm_type": "node", "osm_id": 7702590764, "name": "nan", "full_name": "natural tree", "lat": -36.7536074, "lng": 144.2827613 }, "geometry": { "type": "Point", "coordinates": [ 144.2827613, -36.7536074 ] } },
{ "type": "Feature", "properties": { "osm_type": "node", "osm_id": 7702590763, "name": "nan", "full_name": "natural tree", "lat": -36.7537922, "lng": 144.2837618 }, "geometry": { "type": "Point", "coordinates": [ 144.2837618, -36.7537922 ] } }
]
}
