{
"type": "FeatureCollection",
"crs": { "type": "name", "properties": { "name": "urn:ogc:def:crs:OGC:1.3:CRS84" } },
"features": [
{ "type": "Feature", "properties": { "osm_type": "node", "osm_id": 6417293313, "name": "nan", "full_name": "natural tree source data.gov.au:Hobsons Bay City Council species Eucalyptus cladocalyx circumference 0.45", "lat": -37.862799, "lng": 144.83128 }, "geometry": { "type": "Point", "coordinates": [ 144.83128, -37.862799 ] } },
{ "type": "Feature", "properties": { "osm_type": "node", "osm_id": 6417291909, "name": "nan", "full_name": "natural tree source data.gov.au:Hobsons Bay City Council species Eucalyptus cladocalyx circumference 0.45", "lat": -37.862832, "lng": 144.831523 }, "geometry": { "type": "Point", "coordinates": [ 144.831523, -37.862832 ] } },
{ "type": "Feature", "properties": { "osm_type": "node", "osm_id": 6417291468, "name": "nan", "full_name": "natural tree source data.gov.au:Hobsons Bay City Council species Eucalyptus cladocalyx circumference 0.45", "lat": -37.862789, "lng": 144.83117 }, "geometry": { "type": "Point", "coordinates": [ 144.83117, -37.862789 ] } },
{ "type": "Feature", "properties": { "osm_type": "node", "osm_id": 6417292996, "name": "nan", "full_name": "natural tree source data.gov.au:Hobsons Bay City Council species Eucalyptus cladocalyx circumference 0.75", "lat": -37.862815, "lng": 144.831603 }, "geometry": { "type": "Point", "coordinates": [ 144.831603, -37.862815 ] } },
{ "type": "Feature", "properties": { "osm_type": "node", "osm_id": 6417294549, "name": "nan", "full_name": "natural tree source data.gov.au:Hobsons Bay City Council species Eucalyptus cladocalyx circumference 0.75", "lat": -37.862751, "lng": 144.831151 }, "geometry": { "type": "Point", "coordinates": [ 144.831151, -37.862751 ] } },
{ "type": "Feature", "properties": { "osm_type": "node", "osm_id": 6417293808, "name": "nan", "full_name": "natural tree source data.gov.au:Hobsons Bay City Council species Eucalyptus cladocalyx circumference 0.6", "lat": -37.862721, "lng": 144.832493 }, "geometry": { "type": "Point", "coordinates": [ 144.832493, -37.862721 ] } },
{ "type": "Feature", "properties": { "osm_type": "node", "osm_id": 6417292792, "name": "nan", "full_name": "natural tree source data.gov.au:Hobsons Bay City Council species Eucalyptus cladocalyx circumference 0.6", "lat": -37.862794, "lng": 144.830944 }, "geometry": { "type": "Point", "coordinates": [ 144.830944, -37.862794 ] } },
{ "type": "Feature", "properties": { "osm_type": "node", "osm_id": 6417296086, "name": "nan", "full_name": "natural tree source data.gov.au:Hobsons Bay City Council species Eucalyptus cladocalyx circumference 0.6", "lat": -37.862758, "lng": 144.830825 }, "geometry": { "type": "Point", "coordinates": [ 144.830825, -37.862758 ] } },
{ "type": "Feature", "properties": { "osm_type": "node", "osm_id": 6417292554, "name": "nan", "full_name": "natural tree source data.gov.au:Hobsons Bay City Council species Eucalyptus cladocalyx circumference 0.6", "lat": -37.862785, "lng": 144.831384 }, "geometry": { "type": "Point", "coordinates": [ 144.831384, -37.862785 ] } },
{ "type": "Feature", "properties": { "osm_type": "node", "osm_id": 6417291075, "name": "nan", "full_name": "natural tree source data.gov.au:Hobsons Bay City Council species Eucalyptus cladocalyx circumference 0.6", "lat": -37.862749, "lng": 144.833307 }, "geometry": { "type": "Point", "coordinates": [ 144.833307, -37.862749 ] } }
]
}
